huaweicloudsdkvas/__init__.py
huaweicloudsdkvas/v2/__init__.py
huaweicloudsdkvas/v2/vas_async_client.py
huaweicloudsdkvas/v2/vas_client.py
huaweicloudsdkvas/v2/model/__init__.py
huaweicloudsdkvas/v2/model/create_response_body.py
huaweicloudsdkvas/v2/model/create_tasks_request.py
huaweicloudsdkvas/v2/model/create_tasks_request_body.py
huaweicloudsdkvas/v2/model/create_tasks_response.py
huaweicloudsdkvas/v2/model/delete_task_request.py
huaweicloudsdkvas/v2/model/delete_task_response.py
huaweicloudsdkvas/v2/model/list_tasks_details_request.py
huaweicloudsdkvas/v2/model/list_tasks_details_response.py
huaweicloudsdkvas/v2/model/show_task_request.py
huaweicloudsdkvas/v2/model/show_task_response.py
huaweicloudsdkvas/v2/model/start_task_request.py
huaweicloudsdkvas/v2/model/start_task_response.py
huaweicloudsdkvas/v2/model/stop_task_request.py
huaweicloudsdkvas/v2/model/stop_task_response.py
huaweicloudsdkvas/v2/model/task_details.py
huaweicloudsdkvas/v2/model/task_details_error.py
huaweicloudsdkvas/v2/model/task_details_service_title.py
huaweicloudsdkvas/v2/model/task_hosting_result.py
huaweicloudsdkvas/v2/model/task_hosting_result_hosting_result.py
huaweicloudsdkvas/v2/model/task_input.py
huaweicloudsdkvas/v2/model/task_input_data.py
huaweicloudsdkvas/v2/model/task_input_vcn.py
huaweicloudsdkvas/v2/model/task_output.py
huaweicloudsdkvas/v2/model/task_output_dis.py
huaweicloudsdkvas/v2/model/task_output_for_display.py
huaweicloudsdkvas/v2/model/task_output_hosting.py
huaweicloudsdkvas/v2/model/task_output_hosting_for_display.py
huaweicloudsdkvas/v2/model/task_output_hosting_for_display_obs.py
huaweicloudsdkvas/v2/model/task_output_localpath.py
huaweicloudsdkvas/v2/model/task_output_obs.py
huaweicloudsdkvas/v2/model/task_output_webhook.py
huaweicloudsdkvas/v2/model/task_service_config.py
huaweicloudsdkvas/v2/model/task_timing.py
huaweicloudsdkvas/v2/model/task_timing_frequency.py
huaweicloudsdkvas/v2/model/task_timing_periods.py
huaweicloudsdkvas-3.1.184.dist-info/METADATA
huaweicloudsdkvas-3.1.184.dist-info/WHEEL
huaweicloudsdkvas-3.1.184.dist-info/licenses/LICENSE
huaweicloudsdkvas-3.1.184.dist-info/RECORD
